{
  "userInfo": "token",
  "sysMenuVoList": [
    {
      "id": 1,
      "menuCode": null,
      "menuName": "首页",
      "menuIcon": "el-icon-tickets",
      "menuUrl": null,
      "parentId": "0",
      "orderBy": "1",
      "isShow": 1,
      "resoure_url": "index",
      "resoure_type": "module",
      "permission": "index",
      "sysMenuVoChild": [
        {
          "id": 24,
          "menuCode": null,
          "menuName": "系统首页",
          "menuIcon": "",
          "menuUrl": null,
          "parentId": "1",
          "orderBy": "1",
          "isShow": 1,
          "resoure_url": "",
          "resoure_type": "url",
          "permission": "index",
          "sysMenuVoChild": []
        },
        {
          "id": 26,
          "menuCode": null,
          "menuName": "建议留言",
          "menuIcon": "",
          "menuUrl": null,
          "parentId": "1",
          "orderBy": "2",
          "isShow": 1,
          "resoure_url": "",
          "resoure_type": "url",
          "permission": "msg",
          "sysMenuVoChild": []
        }
      ]
    },
    {
      "id": 2,
      "menuCode": null,
      "menuName": "网站信息配置",
      "menuIcon": "el-icon-edit",
      "menuUrl": null,
      "parentId": "0",
      "orderBy": "2",
      "isShow": 1,
      "resoure_url": null,
      "resoure_type": "module",
      "permission": "2",
      "sysMenuVoChild": [
        {
          "id": 5,
          "menuCode": null,
          "menuName": "网站信息配置",
          "menuIcon": "0",
          "menuUrl": null,
          "parentId": "2",
          "orderBy": "1",
          "isShow": 1,
          "resoure_url": "",
          "resoure_type": "url",
          "permission": "webInfo",
          "sysMenuVoChild": []
        },
        {
          "id": 6,
          "menuCode": null,
          "menuName": "查询输入页",
          "menuIcon": "0",
          "menuUrl": null,
          "parentId": "2",
          "orderBy": "1",
          "isShow": 1,
          "resoure_url": "WorkPiece/index",
          "resoure_type": "url",
          "permission": "searchinput",
          "sysMenuVoChild": []
        },
        {
          "id": 7,
          "menuCode": null,
          "menuName": "标签选项卡",
          "menuIcon": "0",
          "menuUrl": null,
          "parentId": "2",
          "orderBy": "2",
          "isShow": 1,
          "resoure_url": "FlowMonitor/index",
          "resoure_type": "url",
          "permission": "tabpage",
          "sysMenuVoChild": []
        },
        {
          "id": 22,
          "menuCode": null,
          "menuName": "表单页",
          "menuIcon": "",
          "menuUrl": null,
          "parentId": "2",
          "orderBy": "4",
          "isShow": 1,
          "resoure_url": "",
          "resoure_type": "url",
          "permission": "formpage",
          "sysMenuVoChild": []
        },
        {
          "id": 23,
          "menuCode": null,
          "menuName": "树组件页",
          "menuIcon": "",
          "menuUrl": null,
          "parentId": "2",
          "orderBy": "5",
          "isShow": 1,
          "resoure_url": "",
          "resoure_type": "url",
          "permission": "treepage",
          "sysMenuVoChild": []
        },
        {
          "id": 27,
          "menuCode": null,
          "menuName": "综合表单页",
          "menuIcon": "",
          "menuUrl": null,
          "parentId": "2",
          "orderBy": "1",
          "isShow": 1,
          "resoure_url": "",
          "resoure_type": "url",
          "permission": "messageboard",
          "sysMenuVoChild": [
            {
              "id": 29,
              "menuCode": null,
              "menuName": "详情页",
              "menuIcon": "",
              "menuUrl": null,
              "parentId": "27",
              "orderBy": "",
              "isShow": 0,
              "resoure_url": "",
              "resoure_type": "url",
              "permission": "detail",
              "sysMenuVoChild": []
            }
          ]
        },
        {
          "id": 30,
          "menuCode": null,
          "menuName": "富文本编辑器",
          "menuIcon": "",
          "menuUrl": null,
          "parentId": "2",
          "orderBy": "",
          "isShow": 1,
          "resoure_url": "",
          "resoure_type": "url",
          "permission": "ckeditor",
          "sysMenuVoChild": []
        },
        {
          "id": 34,
          "menuCode": null,
          "menuName": "综合表单页2",
          "menuIcon": "",
          "menuUrl": null,
          "parentId": "2",
          "orderBy": "",
          "isShow": 1,
          "resoure_url": "",
          "resoure_type": "url",
          "permission": "messageboard2",
          "sysMenuVoChild": []
        },
        {
          "id": 35,
          "menuCode": null,
          "menuName": "左导航切换效果",
          "menuIcon": "",
          "menuUrl": null,
          "parentId": "2",
          "orderBy": "",
          "isShow": 1,
          "resoure_url": "",
          "resoure_type": "url",
          "permission": "transition",
          "sysMenuVoChild": []
        }
      ]
    },
    {
      "id": 3,
      "menuCode": null,
      "menuName": "首页轮播图",
      "menuIcon": "el-icon-postcard",
      "menuUrl": null,
      "parentId": "0",
      "orderBy": "3",
      "isShow": 1,
      "resoure_url": null,
      "resoure_type": "module",
      "permission": "3",
      "sysMenuVoChild": [
        {
          "id": 7,
          "menuCode": null,
          "menuName": "首页轮播图",
          "menuIcon": "0",
          "menuUrl": null,
          "parentId": "3",
          "orderBy": "1",
          "isShow": 1,
          "resoure_url": "",
          "resoure_type": "url",
          "permission": "banner",
          "sysMenuVoChild": []
        },
        {
          "id": 8,
          "menuCode": null,
          "menuName": "机构管理",
          "menuIcon": "0",
          "menuUrl": null,
          "parentId": "3",
          "orderBy": "1",
          "isShow": 1,
          "resoure_url": "Admin/OrganizationTree",
          "resoure_type": "url",
          "permission": "organizationTree",
          "sysMenuVoChild": []
        },
        {
          "id": 9,
          "menuCode": null,
          "menuName": "用户管理",
          "menuIcon": "0",
          "menuUrl": null,
          "parentId": "3",
          "orderBy": "2",
          "isShow": 1,
          "resoure_url": "Admin/SysUser",
          "resoure_type": "url",
          "permission": "sysUser",
          "sysMenuVoChild": []
        },
        {
          "id": 11,
          "menuCode": null,
          "menuName": "角色管理",
          "menuIcon": "0",
          "menuUrl": null,
          "parentId": "3",
          "orderBy": "4",
          "isShow": 1,
          "resoure_url": "Admin/SysRole",
          "resoure_type": "url",
          "permission": "sysRole",
          "sysMenuVoChild": []
        },
        {
          "id": 12,
          "menuCode": null,
          "menuName": "资源管理",
          "menuIcon": "0",
          "menuUrl": null,
          "parentId": "3",
          "orderBy": "5",
          "isShow": 1,
          "resoure_url": "Admin/SysResource",
          "resoure_type": "url",
          "permission": "sysResource",
          "sysMenuVoChild": []
        },
        {
          "id": 14,
          "menuCode": null,
          "menuName": "菜单管理",
          "menuIcon": "0",
          "menuUrl": null,
          "parentId": "3",
          "orderBy": "7",
          "isShow": 1,
          "resoure_url": "Admin/SysMenu",
          "resoure_type": "url",
          "permission": "sysMenu",
          "sysMenuVoChild": []
        },
        {
          "id": 15,
          "menuCode": null,
          "menuName": "角色资源授权",
          "menuIcon": "0",
          "menuUrl": null,
          "parentId": "3",
          "orderBy": "8",
          "isShow": 1,
          "resoure_url": "Admin/SysAcl",
          "resoure_type": "url",
          "permission": "sysAcl",
          "sysMenuVoChild": []
        }
      ]
    },
    {
      "id": 4,
      "menuCode": null,
      "menuName": "栏目管理",
      "menuIcon": "el-icon-tickets",
      "menuUrl": null,
      "parentId": "0",
      "orderBy": "1",
      "isShow": 1,
      "resoure_url": "category",
      "resoure_type": "module",
      "permission": "category",
      "sysMenuVoChild": [
        {
          "id": 14,
          "menuCode": null,
          "menuName": "栏目管理",
          "menuIcon": "",
          "menuUrl": null,
          "parentId": "1",
          "orderBy": "1",
          "isShow": 1,
          "resoure_url": "",
          "resoure_type": "url",
          "permission": "category",
          "sysMenuVoChild": []
        }
      ]
    },
    {
      "id": 5,
      "menuCode": null,
      "menuName": "内容管理",
      "menuIcon": "el-icon-reading",
      "menuUrl": null,
      "parentId": "0",
      "orderBy": "1",
      "isShow": 1,
      "resoure_url": "article",
      "resoure_type": "module",
      "permission": "article",
      "sysMenuVoChild": [
        {
          "id": 3,
          "menuCode": null,
          "menuName": "内容管理",
          "menuIcon": "",
          "menuUrl": null,
          "parentId": "1",
          "orderBy": "1",
          "isShow": 1,
          "resoure_url": "",
          "resoure_type": "url",
          "permission": "article",
          "sysMenuVoChild": []
        }
      ]
    },
    {
      "id": 6,
      "menuCode": null,
      "menuName": "友情链接",
      "menuIcon": "el-icon-link",
      "menuUrl": null,
      "parentId": "0",
      "orderBy": "1",
      "isShow": 1,
      "resoure_url": "link",
      "resoure_type": "module",
      "permission": "link",
      "sysMenuVoChild": [
        {
          "id": 3,
          "menuCode": null,
          "menuName": "友情链接",
          "menuIcon": "",
          "menuUrl": null,
          "parentId": "1",
          "orderBy": "1",
          "isShow": 1,
          "resoure_url": "",
          "resoure_type": "url",
          "permission": "friendLink",
          "sysMenuVoChild": []
        }
      ]
    },
    {
      "id": 7,
      "menuCode": null,
      "menuName": "招聘管理",
      "menuIcon": "el-icon-receiving",
      "menuUrl": null,
      "parentId": "0",
      "orderBy": "1",
      "isShow": 1,
      "resoure_url": "recruitment",
      "resoure_type": "module",
      "permission": "recruitment",
      "sysMenuVoChild": [
        {
          "id": 3,
          "menuCode": null,
          "menuName": "招聘管理",
          "menuIcon": "",
          "menuUrl": null,
          "parentId": "1",
          "orderBy": "1",
          "isShow": 1,
          "resoure_url": "",
          "resoure_type": "url",
          "permission": "recruitment",
          "sysMenuVoChild": []
        }
      ]
    },
    {
      "id": 8,
      "menuCode": null,
      "menuName": "自定义数据",
      "menuIcon": "el-icon-tickets",
      "menuUrl": null,
      "parentId": "0",
      "orderBy": "1",
      "isShow": 1,
      "resoure_url": "customData",
      "resoure_type": "module",
      "permission": "customData",
      "sysMenuVoChild": [
        {
          "id": 3,
          "menuCode": null,
          "menuName": "自定义数据",
          "menuIcon": "",
          "menuUrl": null,
          "parentId": "1",
          "orderBy": "1",
          "isShow": 1,
          "resoure_url": "",
          "resoure_type": "url",
          "permission": "customdata",
          "sysMenuVoChild": []
        }
      ]
    },
    {
      "id": 9,
      "menuCode": null,
      "menuName": "在线留言",
      "menuIcon": "el-icon-s-comment",
      "menuUrl": null,
      "parentId": "0",
      "orderBy": "1",
      "isShow": 1,
      "resoure_url": "message",
      "resoure_type": "module",
      "permission": "msg",
      "sysMenuVoChild": [
        {
          "id": 3,
          "menuCode": null,
          "menuName": "在线留言",
          "menuIcon": "el-icon-s-comment",
          "menuUrl": null,
          "parentId": "1",
          "orderBy": "1",
          "isShow": 1,
          "resoure_url": "",
          "resoure_type": "url",
          "permission": "msg",
          "sysMenuVoChild": []
        }
      ]
    }
  ]
}
